rer.newsletterplugin.flask-0.2.1-py3.10-nspkg.pth
rer/newsletterplugin/flask/__init__.py
rer/newsletterplugin/flask/configure.zcml
rer/newsletterplugin/flask/interfaces.py
rer/newsletterplugin/flask/permissions.zcml
rer/newsletterplugin/flask/setuphandlers.py
rer/newsletterplugin/flask/testing.py
rer/newsletterplugin/flask/adapter/__init__.py
rer/newsletterplugin/flask/adapter/configure.zcml
rer/newsletterplugin/flask/adapter/flask_adapter.py
rer/newsletterplugin/flask/browser/__init__.py
rer/newsletterplugin/flask/browser/configure.zcml
rer/newsletterplugin/flask/browser/sendmessageview.py
rer/newsletterplugin/flask/browser/templates/.gitkeep
rer/newsletterplugin/flask/browser/templates/sendmessageview.pt
rer/newsletterplugin/flask/locales/README.rst
rer/newsletterplugin/flask/locales/__init__.py
rer/newsletterplugin/flask/locales/rer.newsletterplugin.flask.pot
rer/newsletterplugin/flask/locales/update.py
rer/newsletterplugin/flask/locales/update.sh
rer/newsletterplugin/flask/locales/en/LC_MESSAGES/rer.newsletterplugin.flask.mo
rer/newsletterplugin/flask/locales/en/LC_MESSAGES/rer.newsletterplugin.flask.po
rer/newsletterplugin/flask/locales/it/LC_MESSAGES/rer.newsletterplugin.flask.mo
rer/newsletterplugin/flask/locales/it/LC_MESSAGES/rer.newsletterplugin.flask.po
rer/newsletterplugin/flask/profiles/default/browserlayer.xml
rer/newsletterplugin/flask/profiles/default/catalog.xml
rer/newsletterplugin/flask/profiles/default/metadata.xml
rer/newsletterplugin/flask/profiles/default/registry.xml
rer/newsletterplugin/flask/profiles/default/rolemap.xml
rer/newsletterplugin/flask/profiles/uninstall/browserlayer.xml
rer/newsletterplugin/flask/profiles/uninstall/registry.xml
rer/newsletterplugin/flask/services/__init__.py
rer/newsletterplugin/flask/services/configure.zcml
rer/newsletterplugin/flask/services/send_complete/__init__.py
rer/newsletterplugin/flask/services/send_complete/configure.zcml
rer/newsletterplugin/flask/services/send_complete/post.py
rer.newsletterplugin.flask-0.2.1.dist-info/LICENSE.GPL
rer.newsletterplugin.flask-0.2.1.dist-info/LICENSE.rst
rer.newsletterplugin.flask-0.2.1.dist-info/METADATA
rer.newsletterplugin.flask-0.2.1.dist-info/WHEEL
rer.newsletterplugin.flask-0.2.1.dist-info/entry_points.txt
rer.newsletterplugin.flask-0.2.1.dist-info/namespace_packages.txt
rer.newsletterplugin.flask-0.2.1.dist-info/top_level.txt
rer.newsletterplugin.flask-0.2.1.dist-info/RECORD
