Metadata-Version: 2.1
Name: rer.newsletterplugin.flask
Version: 0.2.1
Summary: Add-on per Plone collegato a rer.newsletter per inviare le mail usando un servizio Flask
Home-page: https://github.com/collective/rer.newsletterplugin.flask
Author: RedTurtle
Author-email: sviluppo@redturtle.it
License: GPL version 2
Project-URL: PyPI, https://pypi.python.org/pypi/rer.newsletterplugin.flask
Project-URL: Source, https://github.com/collective/rer.newsletterplugin.flask
Project-URL: Tracker, https://github.com/collective/rer.newsletterplugin.flask/issues
Keywords: Python Plone
Classifier: Environment :: Web Environment
Classifier: Framework :: Plone
Classifier: Framework :: Plone :: Addon
Classifier: Framework :: Plone :: 5.2
Classifier: Framework :: Plone :: 6.0
Classifier: Programming Language :: Python
Classifier: Programming Language :: Python :: 2.7
Classifier: Programming Language :: Python :: 3.6
Classifier: Programming Language :: Python :: 3.7
Classifier: Programming Language :: Python :: 3.8
Classifier: Programming Language :: Python :: 3.9
Classifier: Operating System :: OS Independent
Classifier: License :: OSI Approved :: GNU General Public License v2 (GPLv2)
Requires-Python: >=3.7
License-File: LICENSE.GPL
License-File: LICENSE.rst
Requires-Dist: setuptools
Requires-Dist: z3c.jbot
Requires-Dist: plone.api >=1.8.4
Requires-Dist: plone.restapi
Requires-Dist: plone.app.dexterity
Requires-Dist: rer.newsletter
Provides-Extra: test
Requires-Dist: plone.app.testing ; extra == 'test'
Requires-Dist: plone.testing >=5.0.0 ; extra == 'test'
Requires-Dist: plone.app.contenttypes ; extra == 'test'
Requires-Dist: plone.app.robotframework[debug] ; extra == 'test'
Requires-Dist: collective.MockMailHost ; extra == 'test'
Requires-Dist: requests-mock ; extra == 'test'
